bottle_mold.py
bottle_mold-0.0.3.dev1.data/scripts/bottle_mold.py
bottle_mold-0.0.3.dev1.dist-info/DESCRIPTION.rst
bottle_mold-0.0.3.dev1.dist-info/LICENSE.txt
bottle_mold-0.0.3.dev1.dist-info/METADATA
bottle_mold-0.0.3.dev1.dist-info/RECORD
bottle_mold-0.0.3.dev1.dist-info/WHEEL
bottle_mold-0.0.3.dev1.dist-info/metadata.json
bottle_mold-0.0.3.dev1.dist-info/top_level.txt
